{
    "problem_statement": "Given the head of a singly linked list containing integers, shift the elements of the linked list to the right by k places and return the head of the modified list. Do not change the values of the nodes, only change the links between nodes.",
    "examples": [
        {
            "input": "head -> 1 -> 2 -> 3 -> 4 -> 5, k = 2",
            "output": "head -> 4 -> 5 -> 1 -> 2 -> 3",
            "explanation": "List after 1 shift to right: head -> 5 -> 1 -> 2 -> 3 -> 4.\nList after 2 shift to right: head -> 4 -> 5 -> 1 -> 2 -> 3."
        },
        {
            "input": "head -> 1 -> 2 -> 3 -> 4 -> 5, k = 4",
            "output": "head -> 2 -> 3 -> 4 -> 5 -> 1",
            "explanation": "List after 1 shift to right: head -> 5 -> 1 -> 2 -> 3 -> 4.\nList after 2 shift to right: head -> 4 -> 5 -> 1 -> 2 -> 3.\nList after 3 shift to right: head -> 3 -> 4 -> 5 -> 1 -> 2.\nList after 4 shift to right: head -> 2 -> 3 -> 4 -> 5 -> 1."
        }
    ]
}